autocorrect_linux/__init__.py
autocorrect_linux/__main__.py
autocorrect_linux/main.py
autocorrect_linux/core/core.py
autocorrect_linux/core/gui.py
autocorrect_linux/core/predict.py
autocorrect_linux/core/utils.py
autocorrect_linux-0.4.3.dist-info/licenses/LICENSE
autocorrect_linux-0.4.3.dist-info/METADATA
autocorrect_linux-0.4.3.dist-info/WHEEL
autocorrect_linux-0.4.3.dist-info/top_level.txt
autocorrect_linux-0.4.3.dist-info/RECORD
