Metadata-Version: 2.4
Name: autocorrect_linux
Version: 0.4.3
Summary: System-wide autocorrect for Linux
Author-email: simon0302010 <simon0302010@gmail.com>
License-Expression: GPL-3.0
Project-URL: Homepage, https://github.com/simon0302010/autocorrect-linux
Classifier: Operating System :: POSIX :: Linux
Requires-Python: <3.13,>=3.9
License-File: LICENSE
Requires-Dist: click
Requires-Dist: pynput
Requires-Dist: requests
Requires-Dist: customtkinter
Requires-Dist: distance
Requires-Dist: tqdm
Requires-Dist: keras
Requires-Dist: tensorflow
Requires-Dist: numpy
Requires-Dist: python-xlib
Dynamic: license-file
